comsar/__init__.py
comsar/tracks/__init__.py
comsar/tracks/_form.py
comsar/tracks/_pitch.py
comsar/tracks/_rhythm.py
comsar/tracks/_timbre.py
comsar/tracks/utilities.py
comsar-0.0.3.dist-info/LICENSE
comsar-0.0.3.dist-info/METADATA
comsar-0.0.3.dist-info/WHEEL
comsar-0.0.3.dist-info/top_level.txt
comsar-0.0.3.dist-info/RECORD
